nmosconnection/__init__.py
nmosconnection/abstractDevice.py
nmosconnection/activator.py
nmosconnection/api.py
nmosconnection/cmExceptions.py
nmosconnection/constants.py
nmosconnection/facadeWrapper.py
nmosconnection/fieldException.py
nmosconnection/nmosDriver.py
nmosconnection/rtpReceiver.py
nmosconnection/rtpSender.py
nmosconnection/sdpFactory.py
nmosconnection/sdpLineParser.py
nmosconnection/sdpManager.py
nmosconnection/sdpParser.py
nmosconnection/service.py
usr/bin/connectionmanagement
connectionmanagement-2.2.9.dist-info/LICENSE.md
connectionmanagement-2.2.9.dist-info/METADATA
connectionmanagement-2.2.9.dist-info/NOTICE.md
connectionmanagement-2.2.9.dist-info/WHEEL
connectionmanagement-2.2.9.dist-info/top_level.txt
connectionmanagement-2.2.9.dist-info/RECORD
