Metadata-Version: 2.1
Name: connectionmanagement
Version: 2.2.9
Summary: Connection Management API implementation
Home-page: https://github.com/bbc/nmos-device-connection-management-ri/
Author: BBC R&D
Author-email: peter.brightwell@bbc.co.uk
License: Apache 2
Platform: UNKNOWN
Requires-Dist: netifaces
Requires-Dist: flask
Requires-Dist: jsonschema
Requires-Dist: gevent
Requires-Dist: mediatimestamp (<2.0.0)
Requires-Dist: requests
Requires-Dist: nmoscommon (>=0.20.0)
Requires-Dist: six
Requires-Dist: nodefacade (>=0.10.1)
Requires-Dist: werkzeug (<1.0.0,>=0.14.1)
